jacotei_api_v1/__init__.py
jacotei_api_v1/client.py
jacotei_api_v1/api/OffersApi.py
jacotei_api_v1/api/__init__.py
jacotei_api_v1/model/Error.py
jacotei_api_v1/model/Offer.py
jacotei_api_v1/model/OfferPrice.py
jacotei_api_v1/model/OfferRejected.py
jacotei_api_v1/model/OfferRequest.py
jacotei_api_v1/model/OfferResponse.py
jacotei_api_v1/model/__init__.py
jacotei_api-1.0.0.dist-info/LICENSE
jacotei_api-1.0.0.dist-info/METADATA
jacotei_api-1.0.0.dist-info/WHEEL
jacotei_api-1.0.0.dist-info/top_level.txt
jacotei_api-1.0.0.dist-info/RECORD
