Metadata-Version: 2.1
Name: jacotei-api
Version: 1.0.0
Summary: SDK for consumption of JáCotei Api
Home-page: https://github.com/jacotei/jacotei-api-sdk-python3
Author: Luis Milanese
Author-email: luis.milanese@jacotei.com.br
License: UNKNOWN
Platform: UNKNOWN
Classifier: Programming Language :: Python :: 3
Classifier: License :: OSI Approved :: MIT License
Classifier: Operating System :: OS Independent
